toolscord/__init__.py
toolscord/banner.py
toolscord/colors.py
toolscord/logger.py
toolscord-0.3.0.dist-info/LICENSE
toolscord-0.3.0.dist-info/METADATA
toolscord-0.3.0.dist-info/WHEEL
toolscord-0.3.0.dist-info/top_level.txt
toolscord-0.3.0.dist-info/RECORD
