Metadata-Version: 2.1
Name: toolscord
Version: 0.3.0
Summary: A customizable terminal UI toolkit with beautiful banners and colored logging
Home-page: https://github.com/bhaskarsaikia-17/toolscord
Author: ToolsCord
Author-email: toolscord.supp@gmail.com
Project-URL: Bug Tracker, https://github.com/bhaskarsaikia-17/toolscord/issues
Project-URL: Documentation, https://github.com/bhaskarsaikia-17/toolscord
Project-URL: Source Code, https://github.com/bhaskarsaikia-17/toolscord
Keywords: terminal,ui,banner,logger,colors,ansi,cli
Classifier: Programming Language :: Python :: 3
Classifier: Programming Language :: Python :: 3.6
Classifier: Programming Language :: Python :: 3.7
Classifier: Programming Language :: Python :: 3.8
Classifier: Programming Language :: Python :: 3.9
Classifier: Programming Language :: Python :: 3.10
Classifier: License :: OSI Approved :: MIT License
Classifier: Operating System :: OS Independent
Classifier: Topic :: Software Development :: Libraries :: Python Modules
Classifier: Topic :: Software Development :: User Interfaces
Classifier: Intended Audience :: Developers
Classifier: Development Status :: 4 - Beta
Requires-Python: >=3.6
License-File: LICENSE
